{
  "workspace_id": "team360_internal",
  "assistant_instance_id": "automation_diagnosis_default",
  "automation_package_id": "pkg_team360_automation_diagnosis",
  "knowledge_scope_id": "ks_team360_automation_diagnosis",
  "answers": [
    {"step_id": "process_to_automate", "answer": {"free_text": "Enviar un reporte semanal desde Excel por email."}},
    {"step_id": "business_pain", "answer": {"free_text": "Se olvidan de enviarlo y ocupa tiempo administrativo."}},
    {"step_id": "systems_involved", "answer": {"selected": ["excel", "email"]}},
    {"step_id": "frequency_volume", "answer": {"selected": ["weekly", "medium_volume"]}},
    {"step_id": "rules_clarity", "answer": {"selected": ["clear"]}},
    {"step_id": "human_dependency", "answer": {"selected": ["low"]}},
    {"step_id": "access_security", "answer": {"selected": ["password"]}},
    {"step_id": "data_sensitivity", "answer": {"selected": ["erp_operational_data"]}},
    {"step_id": "expected_result", "answer": {"free_text": "Reporte armado y enviado sin olvidos."}},
    {"step_id": "economic_impact", "answer": {"selected": ["medium"]}}
  ]
}
